{
    "format_version": "1.8.0",
    "render_controllers": {
        "controller.render.totem": {
            "arrays": {
                "textures": {
                    "Array.default": [
                        "texture.default"
                    ]
                }
            },
            "geometry": "geometry.default",
            "materials": [
                {
                    "*": "material.default"
                }
            ],
            "textures": [
                "Array.default[0]"
            ]
        }
    }
}